LICENSE
README.md
setup.py
mytools_wjs/__init__.py
mytools_wjs/mytools.py
mytools_wjs.egg-info/PKG-INFO
mytools_wjs.egg-info/SOURCES.txt
mytools_wjs.egg-info/dependency_links.txt
mytools_wjs.egg-info/top_level.txt